Metadata-Version: 2.1
Name: timetable-tool
Version: 0.1.1.3
Summary: Scrape a curtin timetable_tool into google calendar
Home-page: https://github.com/kevinglasson/TimetableTool.git
Author: Kevin Glasson
Author-email: kevinglasson+timetable_tool@gmail.com
License: UNKNOWN
Platform: UNKNOWN
Classifier: Development Status :: 3 - Alpha
Classifier: License :: OSI Approved :: MIT License
Classifier: Intended Audience :: Developers
Classifier: Programming Language :: Python :: 3
Requires-Python: >=3
